GOSTnetsraster/__init__.py
GOSTnetsraster/conversion_tables.py
GOSTnetsraster/market_access.py
gostnetsraster-1.0.0.dist-info/licenses/LICENSE
gostnetsraster-1.0.0.dist-info/METADATA
gostnetsraster-1.0.0.dist-info/WHEEL
gostnetsraster-1.0.0.dist-info/top_level.txt
gostnetsraster-1.0.0.dist-info/RECORD
