Metadata-Version: 2.4
Name: GOSTnetsraster
Version: 1.0.0
Summary: Generate travel time rasters from friction surfaces
Author-email: World Bank <github@worldbank.org>
Maintainer-email: "Benjamin P. Stewart" <bstewart@worldbankgroup.org>
License: 
Project-URL: Homepage, https://github.com/worldbank/GOSTNets_Raster
Project-URL: Bug Reports, https://github.com/worldbank/GOSTNets_Raster/issues
Project-URL: Source, https://github.com/worldbank/GOSTNets_Raster
Classifier: Programming Language :: Python :: 3 :: Only
Classifier: Development Status :: 3 - Alpha
Classifier: Intended Audience :: Developers
Classifier: Operating System :: OS Independent
Requires-Python: >=3.9
License-File: LICENSE
Requires-Dist: rasterio
Requires-Dist: geopandas
Requires-Dist: pandas
Requires-Dist: numpy
Requires-Dist: osmnx
Requires-Dist: scikit-image
Requires-Dist: pyproj
Requires-Dist: scipy
Requires-Dist: pandana
Requires-Dist: GOSTNets
Dynamic: license-file
